enable_gen/src/enable_gen.vhd
library IEEE;
use IEEE.std_logic_1164.all;
use ieee.numeric_std.all;

entity enable_gen is
    generic(N: natural := 1);
    port(
        clk: in std_logic;
        rst: in std_logic;
        s_o: out std_logic := '0' 
    );
end;

architecture enable_gen_arch of enable_gen is
    signal dbg: unsigned(N-1 downto 0) := (others => '1');
    begin
    process(clk)
        constant max: unsigned(N-1 downto 0) := (others => '1');
        variable cnt: unsigned(N-1 downto 0) := (others => '0');
    begin
        if(rst = '1') then
            cnt := (others => '0'); 
        elsif(clk = '1') then
            if(cnt = max) then
                s_o <= '1';
            else
                s_o <= '0';
            end if;
            cnt := cnt + 1;
            dbg <= cnt;
        end if;
    end process;
end;

enable_gen/src/enable_gen_tb.vhd
library IEEE;
use IEEE.std_logic_1164.all;

entity enable_gen_tb is
end;

architecture enable_gen_tb_arch of enable_gen_tb is
    -- Component Declaration --
    component enable_gen is
        generic(N: natural := 2);
        port(
            clk: in std_logic;
            rst: in std_logic;
            s_o: out std_logic 
        );
    end component;

    -- Signals Definition --
    signal clk_tb: std_logic := '0';
    signal rst_tb: std_logic := '0';
    signal s_o_tb: std_logic; 
    
begin

    clk_tb <= not clk_tb after 10 ns;

    DUT: enable_gen
        port map(
            clk => clk_tb,
            rst => rst_tb,
            s_o => s_o_tb
        );
            
    TEST: process

    begin
        wait for 20 * 3 ns;
        assert (s_o_tb = '0') report "Enable Gen didn't work" severity failure;
        wait for 20 ns;
        assert (s_o_tb = '1') report "Enable Gen didn't work" severity failure;
        wait for 20 ns;
        assert (s_o_tb = '0') report "Enable Gen didn't work" severity failure;

        wait;

    end process;

end;

enable_gen/sim/enable_gen_tb.vcd
$date
  Sun Sep  5 18:34:18 2021
$end
$version
  GHDL v0
$end
$timescale
  1 fs
$end
$scope module standard $end
$upscope $end
$scope module std_logic_1164 $end
$upscope $end
$scope module numeric_std $end
$upscope $end
$scope module enable_gen_tb $end
$var reg 1 ! clk_tb $end
$var reg 1 " rst_tb $end
$var reg 1 # s_o_tb $end
$scope module dut $end
$var reg 1 $ clk $end
$var reg 1 % rst $end
$var reg 1 & s_o $end
$var reg 2 ' dbg[1:0] $end
$upscope $end
$upscope $end
$enddefinitions $end
#0
0!
0"
0#
0$
0%
0&
b11 '
#10000000
1!
1$
b01 '
#20000000
0!
0$
#30000000
1!
1$
b10 '
#40000000
0!
0$
#50000000
1!
1$
b11 '
#60000000
0!
0$
#70000000
1!
1#
1$
1&
b00 '
#80000000
0!
0$
#90000000
1!
0#
1$
0&
b01 '
#100000000
0!
0$
#110000000
1!
1$
b10 '
#120000000
0!
0$
#130000000
1!
1$
b11 '
#140000000
0!
0$
#150000000
1!
1#
1$
1&
b00 '
#160000000
0!
0$
#170000000
1!
0#
1$
0&
b01 '
#180000000
0!
0$
#190000000
1!
1$
b10 '
#200000000
0!
0$
#210000000
1!
1$
b11 '
#220000000
0!
0$
#230000000
1!
1#
1$
1&
b00 '
#240000000
0!
0$
#250000000
1!
0#
1$
0&
b01 '
#260000000
0!
0$
#270000000
1!
1$
b10 '
#280000000
0!
0$
#290000000
1!
1$
b11 '
#300000000
0!
0$
#310000000
1!
1#
1$
1&
b00 '
#320000000
0!
0$
#330000000
1!
0#
1$
0&
b01 '
#340000000
0!
0$
#350000000
1!
1$
b10 '
#360000000
0!
0$
#370000000
1!
1$
b11 '
#380000000
0!
0$
#390000000
1!
1#
1$
1&
b00 '
#400000000
0!
0$
#410000000
1!
0#
1$
0&
b01 '
#420000000
0!
0$
#430000000
1!
1$
b10 '
#440000000
0!
0$
#450000000
1!
1$
b11 '
#460000000
0!
0$
#470000000
1!
1#
1$
1&
b00 '
#480000000
0!
0$
#490000000
1!
0#
1$
0&
b01 '
#500000000
0!
0$
#510000000
1!
1$
b10 '
#520000000
0!
0$
#530000000
1!
1$
b11 '
#540000000
0!
0$
#550000000
1!
1#
1$
1&
b00 '
#560000000
0!
0$
#570000000
1!
0#
1$
0&
b01 '
#580000000
0!
0$
#590000000
1!
1$
b10 '
#600000000
0!
0$
#610000000
1!
1$
b11 '
#620000000
0!
0$
#630000000
1!
1#
1$
1&
b00 '
#640000000
0!
0$
#650000000
1!
0#
1$
0&
b01 '
#660000000
0!
0$
#670000000
1!
1$
b10 '
#680000000
0!
0$
#690000000
1!
1$
b11 '
#700000000
0!
0$
#710000000
1!
1#
1$
1&
b00 '
#720000000
0!
0$
#730000000
1!
0#
1$
0&
b01 '
#740000000
0!
0$
#750000000
1!
1$
b10 '
#760000000
0!
0$
#770000000
1!
1$
b11 '
#780000000
0!
0$
#790000000
1!
1#
1$
1&
b00 '
#800000000
0!
0$
#810000000
1!
0#
1$
0&
b01 '
#820000000
0!
0$
#830000000
1!
1$
b10 '
#840000000
0!
0$
#850000000
1!
1$
b11 '
#860000000
0!
0$
#870000000
1!
1#
1$
1&
b00 '
#880000000
0!
0$
#890000000
1!
0#
1$
0&
b01 '
#900000000
0!
0$
#910000000
1!
1$
b10 '
#920000000
0!
0$
#930000000
1!
1$
b11 '
#940000000
0!
0$
#950000000
1!
1#
1$
1&
b00 '
#960000000
0!
0$
#970000000
1!
0#
1$
0&
b01 '
#980000000
0!
0$
#990000000
1!
1$
b10 '
