ffd/src/ffd.vhd
library IEEE;
use IEEE.std_logic_1164.all;

entity ffd is
    port(
        d_i: in std_logic;
        en_i: in std_logic;
        clk_i: in std_logic;
        rst_i: in std_logic;
        q_o: out std_logic 
    );
end;

architecture ffd_arch of ffd is
begin
    process(clk_i, rst_i)
    begin
            if rst_i = '1' then
                q_o <= '0';
            elsif clk_i = '1' then
                if en_i = '1' then
                    q_o <= d_i;
                end if;
            end if;
    end process;
end ffd_arch;

counter/src/counter.vhd
library IEEE;
use IEEE.std_logic_1164.all;

entity counter is
    generic(N: natural:= 4);
    port(
        ena: in std_logic;
        rst: in std_logic; 
        clk: in std_logic;
        q: out std_logic_vector(N-1 downto 0)
    );
end;

architecture counter_arch of counter is
    component ffd is
        port(
            d_i: in std_logic;
            en_i: in std_logic;
            clk_i: in std_logic;
            rst_i: in std_logic;
            q_o: out std_logic 
        );
    end component;

    signal ff_wires: std_logic_vector(N downto 0) := (others => '0');
    signal aux2: std_logic_vector(N-1 downto 0) :=  (others => '0');
    signal aux3: std_logic_vector(N-1 downto 0) :=  (others => '0');

    begin
        ff_wires(0) <= ena;
        ffd_i: for i in 0 to N-1 generate
            ff_wires(i+1) <= ff_wires(i) and aux3(i);
            aux2(i) <= aux3(i) xor ff_wires(i);
            ff: ffd port map(
                d_i => aux2(i),
                en_i => '1',
                clk_i => clk,
                rst_i => rst,
                q_o => aux3(i)
            );
            q(i) <= aux3(i);
        end generate;
        
  end;

counter/src/counter_tb.vhd
library IEEE;
use IEEE.std_logic_1164.all;

entity counter_tb is
end;

architecture counter_tb_arch of counter_tb is
    -- Component Declaration --
    component counter is
        generic(N: natural:= 5);
        port(
            ena: in std_logic;
            rst: in std_logic; 
            clk: in std_logic;
            q: out std_logic_vector(N-1 downto 0)
        );
    end component;

    -- Signals Definition --
    signal ena_tb: std_logic := '1';
    signal rst_tb: std_logic := '0';
    signal clk_tb: std_logic := '0';
    signal q_tb: std_logic_vector(4 downto 0) := (others => '0');

begin

    clk_tb <= not clk_tb after 10 ns;

    -- Sequence Goes Here --
    DUT: counter
        port map(
            ena => ena_tb,
            rst => rst_tb,
            clk => clk_tb,
            q => q_tb
        );
    
    TEST: process
    begin
        wait for 20*31 ns;
        assert q_tb = "11111" report "Counter failed" severity failure;
        wait;
    end process;
end;

counter/sim/counter_tb.vcd
$date
  Sun Sep  5 13:33:35 2021
$end
$version
  GHDL v0
$end
$timescale
  1 fs
$end
$scope module standard $end
$upscope $end
$scope module std_logic_1164 $end
$upscope $end
$scope module counter_tb $end
$var reg 1 ! ena_tb $end
$var reg 1 " rst_tb $end
$var reg 1 # clk_tb $end
$var reg 5 $ q_tb[4:0] $end
$scope module dut $end
$var reg 1 % ena $end
$var reg 1 & rst $end
$var reg 1 ' clk $end
$var reg 5 ( q[4:0] $end
$var reg 6 ) ff_wires[5:0] $end
$var reg 5 * aux2[4:0] $end
$var reg 5 + aux3[4:0] $end
$scope module ffd_i(0) $end
$scope module ff $end
$var reg 1 , d_i $end
$var reg 1 - en_i $end
$var reg 1 . clk_i $end
$var reg 1 / rst_i $end
$var reg 1 0 q_o $end
$upscope $end
$upscope $end
$scope module ffd_i(1) $end
$scope module ff $end
$var reg 1 1 d_i $end
$var reg 1 2 en_i $end
$var reg 1 3 clk_i $end
$var reg 1 4 rst_i $end
$var reg 1 5 q_o $end
$upscope $end
$upscope $end
$scope module ffd_i(2) $end
$scope module ff $end
$var reg 1 6 d_i $end
$var reg 1 7 en_i $end
$var reg 1 8 clk_i $end
$var reg 1 9 rst_i $end
$var reg 1 : q_o $end
$upscope $end
$upscope $end
$scope module ffd_i(3) $end
$scope module ff $end
$var reg 1 ; d_i $end
$var reg 1 < en_i $end
$var reg 1 = clk_i $end
$var reg 1 > rst_i $end
$var reg 1 ? q_o $end
$upscope $end
$upscope $end
$scope module ffd_i(4) $end
$scope module ff $end
$var reg 1 @ d_i $end
$var reg 1 A en_i $end
$var reg 1 B clk_i $end
$var reg 1 C rst_i $end
$var reg 1 D q_o $end
$upscope $end
$upscope $end
$upscope $end
$upscope $end
$enddefinitions $end
#0
1!
0"
0#
b00000 $
1%
0&
0'
b00000 (
b000001 )
b00001 *
b00000 +
1,
1-
0.
0/
00
01
12
03
04
05
06
17
08
09
0:
0;
1<
0=
0>
0?
0@
1A
0B
0C
0D
#10000000
1#
b00001 $
1'
b00001 (
b000011 )
b00010 *
b00001 +
0,
1.
10
11
13
18
1=
1B
#20000000
0#
0'
0.
03
08
0=
0B
#30000000
1#
b00010 $
1'
b00010 (
b000001 )
b00011 *
b00010 +
1,
1.
00
11
13
15
06
18
1=
1B
#40000000
0#
0'
0.
03
08
0=
0B
#50000000
1#
b00011 $
1'
b00011 (
b000111 )
b00100 *
b00011 +
0,
1.
10
01
13
16
18
1=
1B
#60000000
0#
0'
0.
03
08
0=
0B
#70000000
1#
b00100 $
1'
b00100 (
b000001 )
b00101 *
b00100 +
1,
1.
00
01
13
05
16
18
1:
0;
1=
1B
#80000000
0#
0'
0.
03
08
0=
0B
#90000000
1#
b00101 $
1'
b00101 (
b000011 )
b00110 *
b00101 +
0,
1.
10
11
13
18
1=
1B
#100000000
0#
0'
0.
03
08
0=
0B
#110000000
1#
b00110 $
1'
b00110 (
b000001 )
b00111 *
b00110 +
1,
1.
00
11
13
15
16
18
0;
1=
1B
#120000000
0#
0'
0.
03
08
0=
0B
#130000000
1#
b00111 $
1'
b00111 (
b001111 )
b01000 *
b00111 +
0,
1.
10
01
13
06
18
1;
1=
1B
#140000000
0#
0'
0.
03
08
0=
0B
#150000000
1#
b01000 $
1'
b01000 (
b000001 )
b01001 *
b01000 +
1,
1.
00
01
13
05
06
18
0:
1;
1=
1?
0@
1B
#160000000
0#
0'
0.
03
08
0=
0B
#170000000
1#
b01001 $
1'
b01001 (
b000011 )
b01010 *
b01001 +
0,
1.
10
11
13
18
1=
1B
#180000000
0#
0'
0.
03
08
0=
0B
#190000000
1#
b01010 $
1'
b01010 (
b000001 )
b01011 *
b01010 +
1,
1.
00
11
13
15
06
18
1=
1B
#200000000
0#
0'
0.
03
08
0=
0B
#210000000
1#
b01011 $
1'
b01011 (
b000111 )
b01100 *
b01011 +
0,
1.
10
01
13
16
18
1=
1B
#220000000
0#
0'
0.
03
08
0=
0B
#230000000
1#
b01100 $
1'
b01100 (
b000001 )
b01101 *
b01100 +
1,
1.
00
01
13
05
16
18
1:
1;
1=
0@
1B
#240000000
0#
0'
0.
03
08
0=
0B
#250000000
1#
b01101 $
1'
b01101 (
b000011 )
b01110 *
b01101 +
0,
1.
10
11
13
18
1=
1B
#260000000
0#
0'
0.
03
08
0=
0B
#270000000
1#
b01110 $
1'
b01110 (
b000001 )
b01111 *
b01110 +
1,
1.
00
11
13
15
16
18
1;
1=
0@
1B
#280000000
0#
0'
0.
03
08
0=
0B
#290000000
1#
b01111 $
1'
b01111 (
b011111 )
b10000 *
b01111 +
0,
1.
10
01
13
06
18
0;
1=
1@
1B
#300000000
0#
0'
0.
03
08
0=
0B
#310000000
1#
b10000 $
1'
b10000 (
b000001 )
b10001 *
b10000 +
1,
1.
00
01
13
05
06
18
0:
0;
1=
0?
1@
1B
1D
#320000000
0#
0'
0.
03
08
0=
0B
#330000000
1#
b10001 $
1'
b10001 (
b000011 )
b10010 *
b10001 +
0,
1.
10
11
13
18
1=
1B
#340000000
0#
0'
0.
03
08
0=
0B
#350000000
1#
b10010 $
1'
b10010 (
b000001 )
b10011 *
b10010 +
1,
1.
00
11
13
15
06
18
1=
1B
#360000000
0#
0'
0.
03
08
0=
0B
#370000000
1#
b10011 $
1'
b10011 (
b000111 )
b10100 *
b10011 +
0,
1.
10
01
13
16
18
1=
1B
#380000000
0#
0'
0.
03
08
0=
0B
#390000000
1#
b10100 $
1'
b10100 (
b000001 )
b10101 *
b10100 +
1,
1.
00
01
13
05
16
18
1:
0;
1=
1B
#400000000
0#
0'
0.
03
08
0=
0B
#410000000
1#
b10101 $
1'
b10101 (
b000011 )
b10110 *
b10101 +
0,
1.
10
11
13
18
1=
1B
#420000000
0#
0'
0.
03
08
0=
0B
#430000000
1#
b10110 $
1'
b10110 (
b000001 )
b10111 *
b10110 +
1,
1.
00
11
13
15
16
18
0;
1=
1B
#440000000
0#
0'
0.
03
08
0=
0B
#450000000
1#
b10111 $
1'
b10111 (
b001111 )
b11000 *
b10111 +
0,
1.
10
01
13
06
18
1;
1=
1B
#460000000
0#
0'
0.
03
08
0=
0B
#470000000
1#
b11000 $
1'
b11000 (
b000001 )
b11001 *
b11000 +
1,
1.
00
01
13
05
06
18
0:
1;
1=
1?
1@
1B
#480000000
0#
0'
0.
03
08
0=
0B
#490000000
1#
b11001 $
1'
b11001 (
b000011 )
b11010 *
b11001 +
0,
1.
10
11
13
18
1=
1B
#500000000
0#
0'
0.
03
08
0=
0B
#510000000
1#
b11010 $
1'
b11010 (
b000001 )
b11011 *
b11010 +
1,
1.
00
11
13
15
06
18
1=
1B
#520000000
0#
0'
0.
03
08
0=
0B
#530000000
1#
b11011 $
1'
b11011 (
b000111 )
b11100 *
b11011 +
0,
1.
10
01
13
16
18
1=
1B
#540000000
0#
0'
0.
03
08
0=
0B
#550000000
1#
b11100 $
1'
b11100 (
b000001 )
b11101 *
b11100 +
1,
1.
00
01
13
05
16
18
1:
1;
1=
1@
1B
#560000000
0#
0'
0.
03
08
0=
0B
#570000000
1#
b11101 $
1'
b11101 (
b000011 )
b11110 *
b11101 +
0,
1.
10
11
13
18
1=
1B
#580000000
0#
0'
0.
03
08
0=
0B
#590000000
1#
b11110 $
1'
b11110 (
b000001 )
b11111 *
b11110 +
1,
1.
00
11
13
15
16
18
1;
1=
1@
1B
#600000000
0#
0'
0.
03
08
0=
0B
#610000000
1#
b11111 $
1'
b11111 (
b111111 )
b00000 *
b11111 +
0,
1.
10
01
13
06
18
0;
1=
0@
1B
#620000000
0#
0'
0.
03
08
0=
0B
#630000000
1#
b00000 $
1'
b00000 (
b000001 )
b00001 *
b00000 +
1,
1.
00
01
13
05
06
18
0:
0;
1=
0?
0@
1B
0D
#640000000
0#
0'
0.
03
08
0=
0B
#650000000
1#
b00001 $
1'
b00001 (
b000011 )
b00010 *
b00001 +
0,
1.
10
11
13
18
1=
1B
#660000000
0#
0'
0.
03
08
0=
0B
#670000000
1#
b00010 $
1'
b00010 (
b000001 )
b00011 *
b00010 +
1,
1.
00
11
13
15
06
18
1=
1B
#680000000
0#
0'
0.
03
08
0=
0B
#690000000
1#
b00011 $
1'
b00011 (
b000111 )
b00100 *
b00011 +
0,
1.
10
01
13
16
18
1=
1B
#700000000
0#
0'
0.
03
08
0=
0B
#710000000
1#
b00100 $
1'
b00100 (
b000001 )
b00101 *
b00100 +
1,
1.
00
01
13
05
16
18
1:
0;
1=
1B
#720000000
0#
0'
0.
03
08
0=
0B
#730000000
1#
b00101 $
1'
b00101 (
b000011 )
b00110 *
b00101 +
0,
1.
10
11
13
18
1=
1B
#740000000
0#
0'
0.
03
08
0=
0B
#750000000
1#
b00110 $
1'
b00110 (
b000001 )
b00111 *
b00110 +
1,
1.
00
11
13
15
16
18
0;
1=
1B
#760000000
0#
0'
0.
03
08
0=
0B
#770000000
1#
b00111 $
1'
b00111 (
b001111 )
b01000 *
b00111 +
0,
1.
10
01
13
06
18
1;
1=
1B
#780000000
0#
0'
0.
03
08
0=
0B
#790000000
1#
b01000 $
1'
b01000 (
b000001 )
b01001 *
b01000 +
1,
1.
00
01
13
05
06
18
0:
1;
1=
1?
0@
1B
#800000000
0#
0'
0.
03
08
0=
0B
#810000000
1#
b01001 $
1'
b01001 (
b000011 )
b01010 *
b01001 +
0,
1.
10
11
13
18
1=
1B
#820000000
0#
0'
0.
03
08
0=
0B
#830000000
1#
b01010 $
1'
b01010 (
b000001 )
b01011 *
b01010 +
1,
1.
00
11
13
15
06
18
1=
1B
#840000000
0#
0'
0.
03
08
0=
0B
#850000000
1#
b01011 $
1'
b01011 (
b000111 )
b01100 *
b01011 +
0,
1.
10
01
13
16
18
1=
1B
#860000000
0#
0'
0.
03
08
0=
0B
#870000000
1#
b01100 $
1'
b01100 (
b000001 )
b01101 *
b01100 +
1,
1.
00
01
13
05
16
18
1:
1;
1=
0@
1B
#880000000
0#
0'
0.
03
08
0=
0B
#890000000
1#
b01101 $
1'
b01101 (
b000011 )
b01110 *
b01101 +
0,
1.
10
11
13
18
1=
1B
#900000000
0#
0'
0.
03
08
0=
0B
#910000000
1#
b01110 $
1'
b01110 (
b000001 )
b01111 *
b01110 +
1,
1.
00
11
13
15
16
18
1;
1=
0@
1B
#920000000
0#
0'
0.
03
08
0=
0B
#930000000
1#
b01111 $
1'
b01111 (
b011111 )
b10000 *
b01111 +
0,
1.
10
01
13
06
18
0;
1=
1@
1B
#940000000
0#
0'
0.
03
08
0=
0B
#950000000
1#
b10000 $
1'
b10000 (
b000001 )
b10001 *
b10000 +
1,
1.
00
01
13
05
06
18
0:
0;
1=
0?
1@
1B
1D
#960000000
0#
0'
0.
03
08
0=
0B
#970000000
1#
b10001 $
1'
b10001 (
b000011 )
b10010 *
b10001 +
0,
1.
10
11
13
18
1=
1B
#980000000
0#
0'
0.
03
08
0=
0B
#990000000
1#
b10010 $
1'
b10010 (
b000001 )
b10011 *
b10010 +
1,
1.
00
11
13
15
06
18
1=
1B
