ffd/src/ffd.vhd
library IEEE;
use IEEE.std_logic_1164.all;

entity ffd is
    port(
        d_i: in std_logic;
        en_i: in std_logic;
        clk_i: in std_logic;
        rst_i: in std_logic;
        q_o: out std_logic := '0'
    );
end;

architecture ffd_arch of ffd is
begin
    process(clk_i, rst_i)
    begin
            if rst_i = '1' then
                q_o <= '0';
            elsif clk_i = '1' then
                if en_i = '1' then
                    q_o <= d_i;
                end if;
            end if;
    end process;
end ffd_arch;

counter/src/counter.vhd
library IEEE;
use IEEE.std_logic_1164.all;

entity counter is
    generic(N: natural:= 4);
    port(
        ena: in std_logic;
        rst: in std_logic; 
        clk: in std_logic;
        q: out std_logic_vector(N-1 downto 0)
    );
end;

architecture counter_arch of counter is
    component ffd is
        port(
            d_i: in std_logic;
            en_i: in std_logic;
            clk_i: in std_logic;
            rst_i: in std_logic;
            q_o: out std_logic 
        );
    end component;

    signal ff_wires: std_logic_vector(N downto 0) := "00000";
    signal aux2: std_logic_vector(N-1 downto 0) :=  "0000";
    signal aux3: std_logic_vector(N-1 downto 0) :=  "0000";

    begin
        ff_wires(0) <= ena;
        ffd_i: for i in 0 to N-1 generate
            ff_wires(i+1) <= ff_wires(i) and aux3(i);
            aux2(i) <= aux3(i) xor ff_wires(i);
            ff: ffd port map(
                d_i => aux2(i),
                en_i => '1',
                clk_i => clk,
                rst_i => rst,
                q_o => aux3(i)
            );
            q(i) <= aux3(i);
        end generate;
        
  end;

counter/src/counter_tb.vhd
library IEEE;
use IEEE.std_logic_1164.all;

entity counter_tb is
end;

architecture counter_tb_arch of counter_tb is
    -- Component Declaration --
    component counter is
        generic(N: natural:= 4);
        port(
            ena: in std_logic;
            rst: in std_logic; 
            clk: in std_logic;
            q: out std_logic_vector(N-1 downto 0)
        );
    end component;

    -- Signals Definition --
    signal ena_tb: std_logic := '1';
    signal rst_tb: std_logic := '0';
    signal clk_tb: std_logic := '0';
    signal q_tb: std_logic_vector(3 downto 0) := "0000";

begin

    clk_tb <= not clk_tb after 10 ns;

    -- Sequence Goes Here --
    DUT: counter
        port map(
            ena => ena_tb,
            rst => rst_tb,
            clk => clk_tb,
            q => q_tb
        );
    
    TEST: process
    begin
        wait for 20*15 ns;
        assert q_tb = "1111" report "Counter failed" severity failure;
        wait;
    end process;
end;

counter/sim/counter_tb.vcd
$date
  Sun Sep  5 13:00:55 2021
$end
$version
  GHDL v0
$end
$timescale
  1 fs
$end
$scope module standard $end
$upscope $end
$scope module std_logic_1164 $end
$upscope $end
$scope module counter_tb $end
$var reg 1 ! ena_tb $end
$var reg 1 " rst_tb $end
$var reg 1 # clk_tb $end
$var reg 4 $ q_tb[3:0] $end
$scope module dut $end
$var reg 1 % ena $end
$var reg 1 & rst $end
$var reg 1 ' clk $end
$var reg 4 ( q[3:0] $end
$var reg 5 ) ff_wires[4:0] $end
$var reg 4 * aux2[3:0] $end
$var reg 4 + aux3[3:0] $end
$scope module ffd_i(0) $end
$scope module ff $end
$var reg 1 , d_i $end
$var reg 1 - en_i $end
$var reg 1 . clk_i $end
$var reg 1 / rst_i $end
$var reg 1 0 q_o $end
$upscope $end
$upscope $end
$scope module ffd_i(1) $end
$scope module ff $end
$var reg 1 1 d_i $end
$var reg 1 2 en_i $end
$var reg 1 3 clk_i $end
$var reg 1 4 rst_i $end
$var reg 1 5 q_o $end
$upscope $end
$upscope $end
$scope module ffd_i(2) $end
$scope module ff $end
$var reg 1 6 d_i $end
$var reg 1 7 en_i $end
$var reg 1 8 clk_i $end
$var reg 1 9 rst_i $end
$var reg 1 : q_o $end
$upscope $end
$upscope $end
$scope module ffd_i(3) $end
$scope module ff $end
$var reg 1 ; d_i $end
$var reg 1 < en_i $end
$var reg 1 = clk_i $end
$var reg 1 > rst_i $end
$var reg 1 ? q_o $end
$upscope $end
$upscope $end
$upscope $end
$upscope $end
$enddefinitions $end
#0
1!
0"
0#
b0000 $
1%
0&
0'
b0000 (
b00001 )
b0001 *
b0000 +
1,
1-
0.
0/
00
01
12
03
04
05
06
17
08
09
0:
0;
1<
0=
0>
0?
#10000000
1#
b0001 $
1'
b0001 (
b00011 )
b0010 *
b0001 +
0,
1.
10
11
13
18
1=
#20000000
0#
0'
0.
03
08
0=
#30000000
1#
b0010 $
1'
b0010 (
b00001 )
b0011 *
b0010 +
1,
1.
00
11
13
15
06
18
1=
#40000000
0#
0'
0.
03
08
0=
#50000000
1#
b0011 $
1'
b0011 (
b00111 )
b0100 *
b0011 +
0,
1.
10
01
13
16
18
1=
#60000000
0#
0'
0.
03
08
0=
#70000000
1#
b0100 $
1'
b0100 (
b00001 )
b0101 *
b0100 +
1,
1.
00
01
13
05
16
18
1:
0;
1=
#80000000
0#
0'
0.
03
08
0=
#90000000
1#
b0101 $
1'
b0101 (
b00011 )
b0110 *
b0101 +
0,
1.
10
11
13
18
1=
#100000000
0#
0'
0.
03
08
0=
#110000000
1#
b0110 $
1'
b0110 (
b00001 )
b0111 *
b0110 +
1,
1.
00
11
13
15
16
18
0;
1=
#120000000
0#
0'
0.
03
08
0=
#130000000
1#
b0111 $
1'
b0111 (
b01111 )
b1000 *
b0111 +
0,
1.
10
01
13
06
18
1;
1=
#140000000
0#
0'
0.
03
08
0=
#150000000
1#
b1000 $
1'
b1000 (
b00001 )
b1001 *
b1000 +
1,
1.
00
01
13
05
06
18
0:
1;
1=
1?
#160000000
0#
0'
0.
03
08
0=
#170000000
1#
b1001 $
1'
b1001 (
b00011 )
b1010 *
b1001 +
0,
1.
10
11
13
18
1=
#180000000
0#
0'
0.
03
08
0=
#190000000
1#
b1010 $
1'
b1010 (
b00001 )
b1011 *
b1010 +
1,
1.
00
11
13
15
06
18
1=
#200000000
0#
0'
0.
03
08
0=
#210000000
1#
b1011 $
1'
b1011 (
b00111 )
b1100 *
b1011 +
0,
1.
10
01
13
16
18
1=
#220000000
0#
0'
0.
03
08
0=
#230000000
1#
b1100 $
1'
b1100 (
b00001 )
b1101 *
b1100 +
1,
1.
00
01
13
05
16
18
1:
1;
1=
#240000000
0#
0'
0.
03
08
0=
#250000000
1#
b1101 $
1'
b1101 (
b00011 )
b1110 *
b1101 +
0,
1.
10
11
13
18
1=
#260000000
0#
0'
0.
03
08
0=
#270000000
1#
b1110 $
1'
b1110 (
b00001 )
b1111 *
b1110 +
1,
1.
00
11
13
15
16
18
1;
1=
#280000000
0#
0'
0.
03
08
0=
#290000000
1#
b1111 $
1'
b1111 (
b11111 )
b0000 *
b1111 +
0,
1.
10
01
13
06
18
0;
1=
#300000000
0#
0'
0.
03
08
0=
#310000000
1#
b0000 $
1'
b0000 (
b00001 )
b0001 *
b0000 +
1,
1.
00
01
13
05
06
18
0:
0;
1=
0?
#320000000
0#
0'
0.
03
08
0=
#330000000
1#
b0001 $
1'
b0001 (
b00011 )
b0010 *
b0001 +
0,
1.
10
11
13
18
1=
#340000000
0#
0'
0.
03
08
0=
#350000000
1#
b0010 $
1'
b0010 (
b00001 )
b0011 *
b0010 +
1,
1.
00
11
13
15
06
18
1=
#360000000
0#
0'
0.
03
08
0=
#370000000
1#
b0011 $
1'
b0011 (
b00111 )
b0100 *
b0011 +
0,
1.
10
01
13
16
18
1=
#380000000
0#
0'
0.
03
08
0=
#390000000
1#
b0100 $
1'
b0100 (
b00001 )
b0101 *
b0100 +
1,
1.
00
01
13
05
16
18
1:
0;
1=
#400000000
0#
0'
0.
03
08
0=
#410000000
1#
b0101 $
1'
b0101 (
b00011 )
b0110 *
b0101 +
0,
1.
10
11
13
18
1=
#420000000
0#
0'
0.
03
08
0=
#430000000
1#
b0110 $
1'
b0110 (
b00001 )
b0111 *
b0110 +
1,
1.
00
11
13
15
16
18
0;
1=
#440000000
0#
0'
0.
03
08
0=
#450000000
1#
b0111 $
1'
b0111 (
b01111 )
b1000 *
b0111 +
0,
1.
10
01
13
06
18
1;
1=
#460000000
0#
0'
0.
03
08
0=
#470000000
1#
b1000 $
1'
b1000 (
b00001 )
b1001 *
b1000 +
1,
1.
00
01
13
05
06
18
0:
1;
1=
1?
#480000000
0#
0'
0.
03
08
0=
#490000000
1#
b1001 $
1'
b1001 (
b00011 )
b1010 *
b1001 +
0,
1.
10
11
13
18
1=
#500000000
0#
0'
0.
03
08
0=
#510000000
1#
b1010 $
1'
b1010 (
b00001 )
b1011 *
b1010 +
1,
1.
00
11
13
15
06
18
1=
#520000000
0#
0'
0.
03
08
0=
#530000000
1#
b1011 $
1'
b1011 (
b00111 )
b1100 *
b1011 +
0,
1.
10
01
13
16
18
1=
#540000000
0#
0'
0.
03
08
0=
#550000000
1#
b1100 $
1'
b1100 (
b00001 )
b1101 *
b1100 +
1,
1.
00
01
13
05
16
18
1:
1;
1=
#560000000
0#
0'
0.
03
08
0=
#570000000
1#
b1101 $
1'
b1101 (
b00011 )
b1110 *
b1101 +
0,
1.
10
11
13
18
1=
#580000000
0#
0'
0.
03
08
0=
#590000000
1#
b1110 $
1'
b1110 (
b00001 )
b1111 *
b1110 +
1,
1.
00
11
13
15
16
18
1;
1=
#600000000
0#
0'
0.
03
08
0=
#610000000
1#
b1111 $
1'
b1111 (
b11111 )
b0000 *
b1111 +
0,
1.
10
01
13
06
18
0;
1=
#620000000
0#
0'
0.
03
08
0=
#630000000
1#
b0000 $
1'
b0000 (
b00001 )
b0001 *
b0000 +
1,
1.
00
01
13
05
06
18
0:
0;
1=
0?
#640000000
0#
0'
0.
03
08
0=
#650000000
1#
b0001 $
1'
b0001 (
b00011 )
b0010 *
b0001 +
0,
1.
10
11
13
18
1=
#660000000
0#
0'
0.
03
08
0=
#670000000
1#
b0010 $
1'
b0010 (
b00001 )
b0011 *
b0010 +
1,
1.
00
11
13
15
06
18
1=
#680000000
0#
0'
0.
03
08
0=
#690000000
1#
b0011 $
1'
b0011 (
b00111 )
b0100 *
b0011 +
0,
1.
10
01
13
16
18
1=
#700000000
0#
0'
0.
03
08
0=
#710000000
1#
b0100 $
1'
b0100 (
b00001 )
b0101 *
b0100 +
1,
1.
00
01
13
05
16
18
1:
0;
1=
#720000000
0#
0'
0.
03
08
0=
#730000000
1#
b0101 $
1'
b0101 (
b00011 )
b0110 *
b0101 +
0,
1.
10
11
13
18
1=
#740000000
0#
0'
0.
03
08
0=
#750000000
1#
b0110 $
1'
b0110 (
b00001 )
b0111 *
b0110 +
1,
1.
00
11
13
15
16
18
0;
1=
#760000000
0#
0'
0.
03
08
0=
#770000000
1#
b0111 $
1'
b0111 (
b01111 )
b1000 *
b0111 +
0,
1.
10
01
13
06
18
1;
1=
#780000000
0#
0'
0.
03
08
0=
#790000000
1#
b1000 $
1'
b1000 (
b00001 )
b1001 *
b1000 +
1,
1.
00
01
13
05
06
18
0:
1;
1=
1?
#800000000
0#
0'
0.
03
08
0=
#810000000
1#
b1001 $
1'
b1001 (
b00011 )
b1010 *
b1001 +
0,
1.
10
11
13
18
1=
#820000000
0#
0'
0.
03
08
0=
#830000000
1#
b1010 $
1'
b1010 (
b00001 )
b1011 *
b1010 +
1,
1.
00
11
13
15
06
18
1=
#840000000
0#
0'
0.
03
08
0=
#850000000
1#
b1011 $
1'
b1011 (
b00111 )
b1100 *
b1011 +
0,
1.
10
01
13
16
18
1=
#860000000
0#
0'
0.
03
08
0=
#870000000
1#
b1100 $
1'
b1100 (
b00001 )
b1101 *
b1100 +
1,
1.
00
01
13
05
16
18
1:
1;
1=
#880000000
0#
0'
0.
03
08
0=
#890000000
1#
b1101 $
1'
b1101 (
b00011 )
b1110 *
b1101 +
0,
1.
10
11
13
18
1=
#900000000
0#
0'
0.
03
08
0=
#910000000
1#
b1110 $
1'
b1110 (
b00001 )
b1111 *
b1110 +
1,
1.
00
11
13
15
16
18
1;
1=
#920000000
0#
0'
0.
03
08
0=
#930000000
1#
b1111 $
1'
b1111 (
b11111 )
b0000 *
b1111 +
0,
1.
10
01
13
06
18
0;
1=
#940000000
0#
0'
0.
03
08
0=
#950000000
1#
b0000 $
1'
b0000 (
b00001 )
b0001 *
b0000 +
1,
1.
00
01
13
05
06
18
0:
0;
1=
0?
#960000000
0#
0'
0.
03
08
0=
#970000000
1#
b0001 $
1'
b0001 (
b00011 )
b0010 *
b0001 +
0,
1.
10
11
13
18
1=
#980000000
0#
0'
0.
03
08
0=
#990000000
1#
b0010 $
1'
b0010 (
b00001 )
b0011 *
b0010 +
1,
1.
00
11
13
15
06
18
1=
