ffd_sync/src/ffd_sync.vhd
library IEEE;
use IEEE.std_logic_1164.all;

entity ffd_sync is
    port(
        d_i: in std_logic;
        en_i: in std_logic;
        clk_i: in std_logic;
        rst_i: in std_logic;
        q_o: out std_logic := '0'
    );
end;

architecture ffd_sync_arch of ffd_sync is
begin
    process(clk_i)
    begin
            if clk_i = '1' then
                if rst_i = '1' then
                    q_o <= '0';
                elsif en_i = '1' then
                    q_o <= d_i;
                end if;
            end if;
    end process;
end ffd_sync_arch;

full_adder/src/full_adder.vhd
library IEEE;
use IEEE.std_logic_1164.all;

entity full_adder is
    port(
        ci_i: in std_logic;
        a_i: in std_logic;
        b_i: in std_logic;
        s_o: out std_logic;
        co_o: out std_logic 
    ) ;
end;

architecture full_adder_arch of full_adder is

begin
    s_o <= a_i xor b_i xor ci_i;
    co_o <= (a_i and b_i) or (ci_i and (a_i xor b_i));
end;

full_adder_4bits/src/full_adder_4bits.vhd
library IEEE;
use IEEE.std_logic_1164.all;

entity full_adder_4bits is
    port(
        a_i: in std_logic_vector(3 downto 0);
        b_i: in std_logic_vector(3 downto 0);
        ci_i: in std_logic;
        s_o: out std_logic_vector(3 downto 0);
        co_o: out std_logic 
    );
end;

architecture full_adder_4bits_arch of full_adder_4bits is
    component full_adder 
    port(
        ci_i: in std_logic;
        a_i: in std_logic;
        b_i: in std_logic;
        s_o: out std_logic;
        co_o: out std_logic 
    );
    end component;

    signal carry_aux: std_logic_vector(4 downto 0);

    begin

        carry_aux(0) <= ci_i;
        add_gen: for add_i in 0 to 3 generate
            add: full_adder port map(
                ci_i => carry_aux(add_i),
                a_i => a_i(add_i),
                b_i => b_i(add_i),
                s_o => s_o(add_i),
                co_o => carry_aux(add_i + 1)     
            );
        end generate;
        co_o <= carry_aux(4);

    end;

mux/src/mux.vhd
library IEEE;
use IEEE.std_logic_1164.all;

entity mux is
    port(
        a_i: in std_logic;
        b_i: in std_logic;
        s_i: in std_logic; 
        q_o: out std_logic
    );
end;

architecture mux_arch of mux is
    begin
        q_o <= (not s_i and a_i) or (s_i and b_i);
    end;

bcd_counter/src/bcd_counter.vhd
library IEEE;
use IEEE.std_logic_1164.all;

entity bcd_counter is
    port(
        en: in std_logic; 
        clk: in std_logic;
        q: out std_logic_vector(3 downto 0) := (others => '0');
        c_o: out std_logic := '0'
    );
end;

architecture bcd_counter_arch of bcd_counter is
    -- Flip Flops D -> 4 bit Register --
    component ffd_sync is
        port(
            d_i: in std_logic;
            en_i: in std_logic;
            clk_i: in std_logic;
            rst_i: in std_logic;
            q_o: out std_logic 
        );
    end component;

    -- 4 Bit Full Adder -> Incrementer --
    component full_adder_4bits is
        port(
            a_i: in std_logic_vector(3 downto 0);
            b_i: in std_logic_vector(3 downto 0);
            ci_i: in std_logic;
            s_o: out std_logic_vector(3 downto 0);
            co_o: out std_logic 
        );
    end component;

    -- Muxes -> Enable --
    component mux is
        port(
            a_i: in std_logic;
            b_i: in std_logic;
            s_i: in std_logic; 
            q_o: out std_logic
        );
    end component;

    signal cmp: std_logic := '0';
    signal mux_to_reg: std_logic_vector(3 downto 0) := (others => '0');
    signal reg_out: std_logic_vector(3 downto 0) := (others => '0');
    signal inc_out: std_logic_vector(3 downto 0) := (others => '0');
    begin
        cnt_i: for i in 0 to 3 generate
            ff: ffd_sync port map(
                d_i => mux_to_reg(i),
                en_i => '1',
                clk_i => clk,
                rst_i => cmp,
                q_o => reg_out(i)
            );
            mx: mux port map(
                a_i => reg_out(i),
                b_i => inc_out(i),
                s_i => en,
                q_o => mux_to_reg(i)
            );
        end generate;

        adder: full_adder_4bits port map(
            a_i => reg_out,
            b_i => "0000",
            ci_i => '1',
            s_o => inc_out 
        );

        cout_delay: ffd_sync port map (
            d_i => cmp,
            en_i => '1',
            clk_i => clk,
            rst_i => '0',
            q_o => c_o
        );

        cmp <= (not ('1' xor reg_out(3))) and  
               (not ('0' xor reg_out(2))) and
               (not ('0' xor reg_out(1))) and
               (not ('1' xor reg_out(0)));
        
        q <= reg_out;
  end;

bcd_counter/src/bcd_counter_tb.vhd
library IEEE;
use IEEE.std_logic_1164.all;

entity bcd_counter_tb is
end;

architecture bcd_counter_tb_arch of bcd_counter_tb is
    -- Component Declaration --
    component bcd_counter is
        port(
            en: in std_logic; 
            clk: in std_logic;
            q: out std_logic_vector(3 downto 0) := (others => '0');
            c_o: out std_logic := '0'
        );
    end component;

    -- Signals Definition --
    signal en_tb: std_logic := '1'; 
    signal clk_tb: std_logic := '0';
    signal q_tb: std_logic_vector(3 downto 0);
    signal c_o_tb: std_logic;

begin

    clk_tb <= not clk_tb after 10 ns;

    -- Sequence Goes Here --
    DUT: bcd_counter
        port map(
            en => en_tb,
            clk => clk_tb,
            q => q_tb,
            c_o => c_o_tb
        );
    
    TEST: process
    begin
        wait for 20*9 ns;
        assert q_tb = "1001" report "bcd_counter failed" severity failure;
        assert c_o_tb = '0'report "bcd_counter failed" severity failure;
        wait for 20 ns;
        assert q_tb = "0000" report "bcd_counter failed" severity failure;
        assert c_o_tb = '1'report "bcd_counter failed" severity failure;
        wait;
    end process;
end;

bcd_counter/sim/bcd_counter_tb.vcd
$date
  Sun Sep  5 17:02:30 2021
$end
$version
  GHDL v0
$end
$timescale
  1 fs
$end
$scope module standard $end
$upscope $end
$scope module std_logic_1164 $end
$upscope $end
$scope module bcd_counter_tb $end
$var reg 1 ! en_tb $end
$var reg 1 " clk_tb $end
$var reg 4 # q_tb[3:0] $end
$var reg 1 $ c_o_tb $end
$scope module dut $end
$var reg 1 % en $end
$var reg 1 & clk $end
$var reg 4 ' q[3:0] $end
$var reg 1 ( c_o $end
$var reg 1 ) cmp $end
$var reg 4 * mux_to_reg[3:0] $end
$var reg 4 + reg_out[3:0] $end
$var reg 4 , inc_out[3:0] $end
$scope module cnt_i(0) $end
$scope module ff $end
$var reg 1 - d_i $end
$var reg 1 . en_i $end
$var reg 1 / clk_i $end
$var reg 1 0 rst_i $end
$var reg 1 1 q_o $end
$upscope $end
$scope module mx $end
$var reg 1 2 a_i $end
$var reg 1 3 b_i $end
$var reg 1 4 s_i $end
$var reg 1 5 q_o $end
$upscope $end
$upscope $end
$scope module cnt_i(1) $end
$scope module ff $end
$var reg 1 6 d_i $end
$var reg 1 7 en_i $end
$var reg 1 8 clk_i $end
$var reg 1 9 rst_i $end
$var reg 1 : q_o $end
$upscope $end
$scope module mx $end
$var reg 1 ; a_i $end
$var reg 1 < b_i $end
$var reg 1 = s_i $end
$var reg 1 > q_o $end
$upscope $end
$upscope $end
$scope module cnt_i(2) $end
$scope module ff $end
$var reg 1 ? d_i $end
$var reg 1 @ en_i $end
$var reg 1 A clk_i $end
$var reg 1 B rst_i $end
$var reg 1 C q_o $end
$upscope $end
$scope module mx $end
$var reg 1 D a_i $end
$var reg 1 E b_i $end
$var reg 1 F s_i $end
$var reg 1 G q_o $end
$upscope $end
$upscope $end
$scope module cnt_i(3) $end
$scope module ff $end
$var reg 1 H d_i $end
$var reg 1 I en_i $end
$var reg 1 J clk_i $end
$var reg 1 K rst_i $end
$var reg 1 L q_o $end
$upscope $end
$scope module mx $end
$var reg 1 M a_i $end
$var reg 1 N b_i $end
$var reg 1 O s_i $end
$var reg 1 P q_o $end
$upscope $end
$upscope $end
$scope module adder $end
$var reg 4 Q a_i[3:0] $end
$var reg 4 R b_i[3:0] $end
$var reg 1 S ci_i $end
$var reg 4 T s_o[3:0] $end
$var reg 1 U co_o $end
$var reg 5 V carry_aux[4:0] $end
$scope module add_gen(0) $end
$scope module add $end
$var reg 1 W ci_i $end
$var reg 1 X a_i $end
$var reg 1 Y b_i $end
$var reg 1 Z s_o $end
$var reg 1 [ co_o $end
$upscope $end
$upscope $end
$scope module add_gen(1) $end
$scope module add $end
$var reg 1 \ ci_i $end
$var reg 1 ] a_i $end
$var reg 1 ^ b_i $end
$var reg 1 _ s_o $end
$var reg 1 ` co_o $end
$upscope $end
$upscope $end
$scope module add_gen(2) $end
$scope module add $end
$var reg 1 a ci_i $end
$var reg 1 b a_i $end
$var reg 1 c b_i $end
$var reg 1 d s_o $end
$var reg 1 e co_o $end
$upscope $end
$upscope $end
$scope module add_gen(3) $end
$scope module add $end
$var reg 1 f ci_i $end
$var reg 1 g a_i $end
$var reg 1 h b_i $end
$var reg 1 i s_o $end
$var reg 1 j co_o $end
$upscope $end
$upscope $end
$upscope $end
$scope module cout_delay $end
$var reg 1 k d_i $end
$var reg 1 l en_i $end
$var reg 1 m clk_i $end
$var reg 1 n rst_i $end
$var reg 1 o q_o $end
$upscope $end
$upscope $end
$upscope $end
$enddefinitions $end
#0
1!
0"
b0000 #
0$
1%
0&
b0000 '
0(
0)
b0001 *
b0000 +
b0001 ,
1-
1.
0/
00
01
02
13
14
15
06
17
08
09
0:
0;
0<
1=
0>
0?
1@
0A
0B
0C
0D
0E
1F
0G
0H
1I
0J
0K
0L
0M
0N
1O
0P
b0000 Q
b0000 R
1S
b0001 T
0U
b00001 V
1W
0X
0Y
1Z
0[
0\
0]
0^
0_
0`
0a
0b
0c
0d
0e
0f
0g
0h
0i
0j
0k
1l
0m
0n
0o
#10000000
1"
b0001 #
1&
b0001 '
b0010 *
b0001 +
b0010 ,
0-
1/
11
12
03
05
16
18
1<
1>
1A
1J
b0001 Q
b0010 T
b00011 V
1X
0Z
1[
1\
1_
1m
#20000000
0"
0&
0/
08
0A
0J
0m
#30000000
1"
b0010 #
1&
b0010 '
b0011 *
b0010 +
b0011 ,
1-
1/
01
02
13
15
16
18
1:
1;
1<
1>
0?
1A
0E
0G
1J
b0010 Q
b0011 T
b00001 V
0X
1Z
0[
0\
1]
1_
0`
0a
0d
1m
#40000000
0"
0&
0/
08
0A
0J
0m
#50000000
1"
b0011 #
1&
b0011 '
b0100 *
b0011 +
b0100 ,
0-
1/
11
12
03
05
06
18
0<
0>
1?
1A
1E
1G
1J
b0011 Q
b0100 T
b00111 V
1X
0Z
1[
1\
0_
1`
1a
1d
1m
#60000000
0"
0&
0/
08
0A
0J
0m
#70000000
1"
b0100 #
1&
b0100 '
b0101 *
b0100 +
b0101 ,
1-
1/
01
02
13
15
06
18
0:
0;
0<
0>
1?
1A
1C
1D
1E
1G
0H
1J
0N
0P
b0100 Q
b0101 T
b00001 V
0X
1Z
0[
0\
0]
0_
0`
0a
1b
1d
0e
0f
0i
1m
#80000000
0"
0&
0/
08
0A
0J
0m
#90000000
1"
b0101 #
1&
b0101 '
b0110 *
b0101 +
b0110 ,
0-
1/
11
12
03
05
16
18
1<
1>
1A
1J
b0101 Q
b0110 T
b00011 V
1X
0Z
1[
1\
1_
1m
#100000000
0"
0&
0/
08
0A
0J
0m
#110000000
1"
b0110 #
1&
b0110 '
b0111 *
b0110 +
b0111 ,
1-
1/
01
02
13
15
16
18
1:
1;
1<
1>
1?
1A
1E
1G
0H
1J
0N
0P
b0110 Q
b0111 T
b00001 V
0X
1Z
0[
0\
1]
1_
0`
0a
1d
0e
0f
0i
1m
#120000000
0"
0&
0/
08
0A
0J
0m
#130000000
1"
b0111 #
1&
b0111 '
b1000 *
b0111 +
b1000 ,
0-
1/
11
12
03
05
06
18
0<
0>
0?
1A
0E
0G
1H
1J
1N
1P
b0111 Q
b1000 T
b01111 V
1X
0Z
1[
1\
0_
1`
1a
0d
1e
1f
1i
1m
#140000000
0"
0&
0/
08
0A
0J
0m
#150000000
1"
b1000 #
1&
b1000 '
b1001 *
b1000 +
b1001 ,
1-
1/
01
02
13
15
06
18
0:
0;
0<
0>
0?
1A
0C
0D
0E
0G
1H
1J
1L
1M
1N
1P
b1000 Q
b1001 T
0U
b00001 V
0X
1Z
0[
0\
0]
0_
0`
0a
0b
0d
0e
0f
1g
1i
0j
1m
#160000000
0"
0&
0/
08
0A
0J
0m
#170000000
1"
b1001 #
1&
b1001 '
1)
b1010 *
b1001 +
b1010 ,
0-
1/
10
11
12
03
05
16
18
19
1<
1>
1A
1B
1J
1K
b1001 Q
b1010 T
b00011 V
1X
0Z
1[
1\
1_
1k
1m
#180000000
0"
0&
0/
08
0A
0J
0m
#190000000
1"
b0000 #
1$
1&
b0000 '
1(
0)
b0001 *
b0000 +
b0001 ,
1-
1/
00
01
02
13
15
06
18
09
0<
0>
1A
0B
0H
1J
0K
0L
0M
0N
0P
b0000 Q
b0001 T
b00001 V
0X
1Z
0[
0\
0_
0g
0i
0k
1m
1o
#200000000
0"
0&
0/
08
0A
0J
0m
#210000000
1"
b0001 #
0$
1&
b0001 '
0(
b0010 *
b0001 +
b0010 ,
0-
1/
11
12
03
05
16
18
1<
1>
1A
1J
b0001 Q
b0010 T
b00011 V
1X
0Z
1[
1\
1_
1m
0o
#220000000
0"
0&
0/
08
0A
0J
0m
#230000000
1"
b0010 #
1&
b0010 '
b0011 *
b0010 +
b0011 ,
1-
1/
01
02
13
15
16
18
1:
1;
1<
1>
0?
1A
0E
0G
1J
b0010 Q
b0011 T
b00001 V
0X
1Z
0[
0\
1]
1_
0`
0a
0d
1m
#240000000
0"
0&
0/
08
0A
0J
0m
#250000000
1"
b0011 #
1&
b0011 '
b0100 *
b0011 +
b0100 ,
0-
1/
11
12
03
05
06
18
0<
0>
1?
1A
1E
1G
1J
b0011 Q
b0100 T
b00111 V
1X
0Z
1[
1\
0_
1`
1a
1d
1m
#260000000
0"
0&
0/
08
0A
0J
0m
#270000000
1"
b0100 #
1&
b0100 '
b0101 *
b0100 +
b0101 ,
1-
1/
01
02
13
15
06
18
0:
0;
0<
0>
1?
1A
1C
1D
1E
1G
0H
1J
0N
0P
b0100 Q
b0101 T
b00001 V
0X
1Z
0[
0\
0]
0_
0`
0a
1b
1d
0e
0f
0i
1m
#280000000
0"
0&
0/
08
0A
0J
0m
#290000000
1"
b0101 #
1&
b0101 '
b0110 *
b0101 +
b0110 ,
0-
1/
11
12
03
05
16
18
1<
1>
1A
1J
b0101 Q
b0110 T
b00011 V
1X
0Z
1[
1\
1_
1m
#300000000
0"
0&
0/
08
0A
0J
0m
#310000000
1"
b0110 #
1&
b0110 '
b0111 *
b0110 +
b0111 ,
1-
1/
01
02
13
15
16
18
1:
1;
1<
1>
1?
1A
1E
1G
0H
1J
0N
0P
b0110 Q
b0111 T
b00001 V
0X
1Z
0[
0\
1]
1_
0`
0a
1d
0e
0f
0i
1m
#320000000
0"
0&
0/
08
0A
0J
0m
#330000000
1"
b0111 #
1&
b0111 '
b1000 *
b0111 +
b1000 ,
0-
1/
11
12
03
05
06
18
0<
0>
0?
1A
0E
0G
1H
1J
1N
1P
b0111 Q
b1000 T
b01111 V
1X
0Z
1[
1\
0_
1`
1a
0d
1e
1f
1i
1m
#340000000
0"
0&
0/
08
0A
0J
0m
#350000000
1"
b1000 #
1&
b1000 '
b1001 *
b1000 +
b1001 ,
1-
1/
01
02
13
15
06
18
0:
0;
0<
0>
0?
1A
0C
0D
0E
0G
1H
1J
1L
1M
1N
1P
b1000 Q
b1001 T
0U
b00001 V
0X
1Z
0[
0\
0]
0_
0`
0a
0b
0d
0e
0f
1g
1i
0j
1m
#360000000
0"
0&
0/
08
0A
0J
0m
#370000000
1"
b1001 #
1&
b1001 '
1)
b1010 *
b1001 +
b1010 ,
0-
1/
10
11
12
03
05
16
18
19
1<
1>
1A
1B
1J
1K
b1001 Q
b1010 T
b00011 V
1X
0Z
1[
1\
1_
1k
1m
#380000000
0"
0&
0/
08
0A
0J
0m
#390000000
1"
b0000 #
1$
1&
b0000 '
1(
0)
b0001 *
b0000 +
b0001 ,
1-
1/
00
01
02
13
15
06
18
09
0<
0>
1A
0B
0H
1J
0K
0L
0M
0N
0P
b0000 Q
b0001 T
b00001 V
0X
1Z
0[
0\
0_
0g
0i
0k
1m
1o
#400000000
0"
0&
0/
08
0A
0J
0m
#410000000
1"
b0001 #
0$
1&
b0001 '
0(
b0010 *
b0001 +
b0010 ,
0-
1/
11
12
03
05
16
18
1<
1>
1A
1J
b0001 Q
b0010 T
b00011 V
1X
0Z
1[
1\
1_
1m
0o
#420000000
0"
0&
0/
08
0A
0J
0m
#430000000
1"
b0010 #
1&
b0010 '
b0011 *
b0010 +
b0011 ,
1-
1/
01
02
13
15
16
18
1:
1;
1<
1>
0?
1A
0E
0G
1J
b0010 Q
b0011 T
b00001 V
0X
1Z
0[
0\
1]
1_
0`
0a
0d
1m
#440000000
0"
0&
0/
08
0A
0J
0m
#450000000
1"
b0011 #
1&
b0011 '
b0100 *
b0011 +
b0100 ,
0-
1/
11
12
03
05
06
18
0<
0>
1?
1A
1E
1G
1J
b0011 Q
b0100 T
b00111 V
1X
0Z
1[
1\
0_
1`
1a
1d
1m
#460000000
0"
0&
0/
08
0A
0J
0m
#470000000
1"
b0100 #
1&
b0100 '
b0101 *
b0100 +
b0101 ,
1-
1/
01
02
13
15
06
18
0:
0;
0<
0>
1?
1A
1C
1D
1E
1G
0H
1J
0N
0P
b0100 Q
b0101 T
b00001 V
0X
1Z
0[
0\
0]
0_
0`
0a
1b
1d
0e
0f
0i
1m
#480000000
0"
0&
0/
08
0A
0J
0m
#490000000
1"
b0101 #
1&
b0101 '
b0110 *
b0101 +
b0110 ,
0-
1/
11
12
03
05
16
18
1<
1>
1A
1J
b0101 Q
b0110 T
b00011 V
1X
0Z
1[
1\
1_
1m
#500000000
0"
0&
0/
08
0A
0J
0m
#510000000
1"
b0110 #
1&
b0110 '
b0111 *
b0110 +
b0111 ,
1-
1/
01
02
13
15
16
18
1:
1;
1<
1>
1?
1A
1E
1G
0H
1J
0N
0P
b0110 Q
b0111 T
b00001 V
0X
1Z
0[
0\
1]
1_
0`
0a
1d
0e
0f
0i
1m
#520000000
0"
0&
0/
08
0A
0J
0m
#530000000
1"
b0111 #
1&
b0111 '
b1000 *
b0111 +
b1000 ,
0-
1/
11
12
03
05
06
18
0<
0>
0?
1A
0E
0G
1H
1J
1N
1P
b0111 Q
b1000 T
b01111 V
1X
0Z
1[
1\
0_
1`
1a
0d
1e
1f
1i
1m
#540000000
0"
0&
0/
08
0A
0J
0m
#550000000
1"
b1000 #
1&
b1000 '
b1001 *
b1000 +
b1001 ,
1-
1/
01
02
13
15
06
18
0:
0;
0<
0>
0?
1A
0C
0D
0E
0G
1H
1J
1L
1M
1N
1P
b1000 Q
b1001 T
0U
b00001 V
0X
1Z
0[
0\
0]
0_
0`
0a
0b
0d
0e
0f
1g
1i
0j
1m
#560000000
0"
0&
0/
08
0A
0J
0m
#570000000
1"
b1001 #
1&
b1001 '
1)
b1010 *
b1001 +
b1010 ,
0-
1/
10
11
12
03
05
16
18
19
1<
1>
1A
1B
1J
1K
b1001 Q
b1010 T
b00011 V
1X
0Z
1[
1\
1_
1k
1m
#580000000
0"
0&
0/
08
0A
0J
0m
#590000000
1"
b0000 #
1$
1&
b0000 '
1(
0)
b0001 *
b0000 +
b0001 ,
1-
1/
00
01
02
13
15
06
18
09
0<
0>
1A
0B
0H
1J
0K
0L
0M
0N
0P
b0000 Q
b0001 T
b00001 V
0X
1Z
0[
0\
0_
0g
0i
0k
1m
1o
#600000000
0"
0&
0/
08
0A
0J
0m
#610000000
1"
b0001 #
0$
1&
b0001 '
0(
b0010 *
b0001 +
b0010 ,
0-
1/
11
12
03
05
16
18
1<
1>
1A
1J
b0001 Q
b0010 T
b00011 V
1X
0Z
1[
1\
1_
1m
0o
#620000000
0"
0&
0/
08
0A
0J
0m
#630000000
1"
b0010 #
1&
b0010 '
b0011 *
b0010 +
b0011 ,
1-
1/
01
02
13
15
16
18
1:
1;
1<
1>
0?
1A
0E
0G
1J
b0010 Q
b0011 T
b00001 V
0X
1Z
0[
0\
1]
1_
0`
0a
0d
1m
#640000000
0"
0&
0/
08
0A
0J
0m
#650000000
1"
b0011 #
1&
b0011 '
b0100 *
b0011 +
b0100 ,
0-
1/
11
12
03
05
06
18
0<
0>
1?
1A
1E
1G
1J
b0011 Q
b0100 T
b00111 V
1X
0Z
1[
1\
0_
1`
1a
1d
1m
#660000000
0"
0&
0/
08
0A
0J
0m
#670000000
1"
b0100 #
1&
b0100 '
b0101 *
b0100 +
b0101 ,
1-
1/
01
02
13
15
06
18
0:
0;
0<
0>
1?
1A
1C
1D
1E
1G
0H
1J
0N
0P
b0100 Q
b0101 T
b00001 V
0X
1Z
0[
0\
0]
0_
0`
0a
1b
1d
0e
0f
0i
1m
#680000000
0"
0&
0/
08
0A
0J
0m
#690000000
1"
b0101 #
1&
b0101 '
b0110 *
b0101 +
b0110 ,
0-
1/
11
12
03
05
16
18
1<
1>
1A
1J
b0101 Q
b0110 T
b00011 V
1X
0Z
1[
1\
1_
1m
#700000000
0"
0&
0/
08
0A
0J
0m
#710000000
1"
b0110 #
1&
b0110 '
b0111 *
b0110 +
b0111 ,
1-
1/
01
02
13
15
16
18
1:
1;
1<
1>
1?
1A
1E
1G
0H
1J
0N
0P
b0110 Q
b0111 T
b00001 V
0X
1Z
0[
0\
1]
1_
0`
0a
1d
0e
0f
0i
1m
#720000000
0"
0&
0/
08
0A
0J
0m
#730000000
1"
b0111 #
1&
b0111 '
b1000 *
b0111 +
b1000 ,
0-
1/
11
12
03
05
06
18
0<
0>
0?
1A
0E
0G
1H
1J
1N
1P
b0111 Q
b1000 T
b01111 V
1X
0Z
1[
1\
0_
1`
1a
0d
1e
1f
1i
1m
#740000000
0"
0&
0/
08
0A
0J
0m
#750000000
1"
b1000 #
1&
b1000 '
b1001 *
b1000 +
b1001 ,
1-
1/
01
02
13
15
06
18
0:
0;
0<
0>
0?
1A
0C
0D
0E
0G
1H
1J
1L
1M
1N
1P
b1000 Q
b1001 T
0U
b00001 V
0X
1Z
0[
0\
0]
0_
0`
0a
0b
0d
0e
0f
1g
1i
0j
1m
#760000000
0"
0&
0/
08
0A
0J
0m
#770000000
1"
b1001 #
1&
b1001 '
1)
b1010 *
b1001 +
b1010 ,
0-
1/
10
11
12
03
05
16
18
19
1<
1>
1A
1B
1J
1K
b1001 Q
b1010 T
b00011 V
1X
0Z
1[
1\
1_
1k
1m
#780000000
0"
0&
0/
08
0A
0J
0m
#790000000
1"
b0000 #
1$
1&
b0000 '
1(
0)
b0001 *
b0000 +
b0001 ,
1-
1/
00
01
02
13
15
06
18
09
0<
0>
1A
0B
0H
1J
0K
0L
0M
0N
0P
b0000 Q
b0001 T
b00001 V
0X
1Z
0[
0\
0_
0g
0i
0k
1m
1o
#800000000
0"
0&
0/
08
0A
0J
0m
#810000000
1"
b0001 #
0$
1&
b0001 '
0(
b0010 *
b0001 +
b0010 ,
0-
1/
11
12
03
05
16
18
1<
1>
1A
1J
b0001 Q
b0010 T
b00011 V
1X
0Z
1[
1\
1_
1m
0o
#820000000
0"
0&
0/
08
0A
0J
0m
#830000000
1"
b0010 #
1&
b0010 '
b0011 *
b0010 +
b0011 ,
1-
1/
01
02
13
15
16
18
1:
1;
1<
1>
0?
1A
0E
0G
1J
b0010 Q
b0011 T
b00001 V
0X
1Z
0[
0\
1]
1_
0`
0a
0d
1m
#840000000
0"
0&
0/
08
0A
0J
0m
#850000000
1"
b0011 #
1&
b0011 '
b0100 *
b0011 +
b0100 ,
0-
1/
11
12
03
05
06
18
0<
0>
1?
1A
1E
1G
1J
b0011 Q
b0100 T
b00111 V
1X
0Z
1[
1\
0_
1`
1a
1d
1m
#860000000
0"
0&
0/
08
0A
0J
0m
#870000000
1"
b0100 #
1&
b0100 '
b0101 *
b0100 +
b0101 ,
1-
1/
01
02
13
15
06
18
0:
0;
0<
0>
1?
1A
1C
1D
1E
1G
0H
1J
0N
0P
b0100 Q
b0101 T
b00001 V
0X
1Z
0[
0\
0]
0_
0`
0a
1b
1d
0e
0f
0i
1m
#880000000
0"
0&
0/
08
0A
0J
0m
#890000000
1"
b0101 #
1&
b0101 '
b0110 *
b0101 +
b0110 ,
0-
1/
11
12
03
05
16
18
1<
1>
1A
1J
b0101 Q
b0110 T
b00011 V
1X
0Z
1[
1\
1_
1m
#900000000
0"
0&
0/
08
0A
0J
0m
#910000000
1"
b0110 #
1&
b0110 '
b0111 *
b0110 +
b0111 ,
1-
1/
01
02
13
15
16
18
1:
1;
1<
1>
1?
1A
1E
1G
0H
1J
0N
0P
b0110 Q
b0111 T
b00001 V
0X
1Z
0[
0\
1]
1_
0`
0a
1d
0e
0f
0i
1m
#920000000
0"
0&
0/
08
0A
0J
0m
#930000000
1"
b0111 #
1&
b0111 '
b1000 *
b0111 +
b1000 ,
0-
1/
11
12
03
05
06
18
0<
0>
0?
1A
0E
0G
1H
1J
1N
1P
b0111 Q
b1000 T
b01111 V
1X
0Z
1[
1\
0_
1`
1a
0d
1e
1f
1i
1m
#940000000
0"
0&
0/
08
0A
0J
0m
#950000000
1"
b1000 #
1&
b1000 '
b1001 *
b1000 +
b1001 ,
1-
1/
01
02
13
15
06
18
0:
0;
0<
0>
0?
1A
0C
0D
0E
0G
1H
1J
1L
1M
1N
1P
b1000 Q
b1001 T
0U
b00001 V
0X
1Z
0[
0\
0]
0_
0`
0a
0b
0d
0e
0f
1g
1i
0j
1m
#960000000
0"
0&
0/
08
0A
0J
0m
#970000000
1"
b1001 #
1&
b1001 '
1)
b1010 *
b1001 +
b1010 ,
0-
1/
10
11
12
03
05
16
18
19
1<
1>
1A
1B
1J
1K
b1001 Q
b1010 T
b00011 V
1X
0Z
1[
1\
1_
1k
1m
#980000000
0"
0&
0/
08
0A
0J
0m
#990000000
1"
b0000 #
1$
1&
b0000 '
1(
0)
b0001 *
b0000 +
b0001 ,
1-
1/
00
01
02
13
15
06
18
09
0<
0>
1A
0B
0H
1J
0K
0L
0M
0N
0P
b0000 Q
b0001 T
b00001 V
0X
1Z
0[
0\
0_
0g
0i
0k
1m
1o
