counter_behavioral/src/counter_behavioral.vhd
library IEEE;
use ieee.std_logic_1164.all;
use ieee.numeric_std.all;

entity counter_behavioral is
    generic(N: natural:= 4);
    port(
        ena: in std_logic;
        rst: in std_logic; 
        clk: in std_logic;
        q: out std_logic_vector(N-1 downto 0) := (others => '0')
    );
end;

architecture counter_behavioral_arch of counter_behavioral is
    begin 
    process(clk, rst)
        variable cnt: unsigned(N-1 downto 0) := (others => '0');
    begin
        if(rst = '1') then
            cnt := (others => '0');
        elsif((ena = '1') and (clk = '1')) then
            cnt := cnt + 1;
            q <= std_logic_vector(cnt);
        end if;
    end process;   
  end;

counter_behavioral/src/counter_behavioral_tb.vhd
library IEEE;
use IEEE.std_logic_1164.all;

entity counter_behavioral_tb is
end;

architecture counter_behavioral_tb_arch of counter_behavioral_tb is
    -- Component Declaration --
    component counter_behavioral is
        generic(N: natural:= 5);
        port(
            ena: in std_logic;
            rst: in std_logic; 
            clk: in std_logic;
            q: out std_logic_vector(N-1 downto 0)
        );
    end component;

    -- Signals Definition --
    signal ena_tb: std_logic := '1';
    signal rst_tb: std_logic := '0';
    signal clk_tb: std_logic := '0';
    signal q_tb: std_logic_vector(4 downto 0) := (others => '0');

begin

    clk_tb <= not clk_tb after 10 ns;

    -- Sequence Goes Here --
    DUT: counter_behavioral
        port map(
            ena => ena_tb,
            rst => rst_tb,
            clk => clk_tb,
            q => q_tb
        );
    
    TEST: process
    begin
        wait for 20*31 ns;
        assert q_tb = "11111" report "counter_behavioral failed" severity failure;
        wait;
    end process;
end;

counter_behavioral/sim/counter_behavioral_tb.vcd
$date
  Sun Sep  5 13:34:42 2021
$end
$version
  GHDL v0
$end
$timescale
  1 fs
$end
$scope module standard $end
$upscope $end
$scope module std_logic_1164 $end
$upscope $end
$scope module numeric_std $end
$upscope $end
$scope module counter_behavioral_tb $end
$var reg 1 ! ena_tb $end
$var reg 1 " rst_tb $end
$var reg 1 # clk_tb $end
$var reg 5 $ q_tb[4:0] $end
$scope module dut $end
$var reg 1 % ena $end
$var reg 1 & rst $end
$var reg 1 ' clk $end
$var reg 5 ( q[4:0] $end
$upscope $end
$upscope $end
$enddefinitions $end
#0
1!
0"
0#
b00000 $
1%
0&
0'
b00000 (
#10000000
1#
b00001 $
1'
b00001 (
#20000000
0#
0'
#30000000
1#
b00010 $
1'
b00010 (
#40000000
0#
0'
#50000000
1#
b00011 $
1'
b00011 (
#60000000
0#
0'
#70000000
1#
b00100 $
1'
b00100 (
#80000000
0#
0'
#90000000
1#
b00101 $
1'
b00101 (
#100000000
0#
0'
#110000000
1#
b00110 $
1'
b00110 (
#120000000
0#
0'
#130000000
1#
b00111 $
1'
b00111 (
#140000000
0#
0'
#150000000
1#
b01000 $
1'
b01000 (
#160000000
0#
0'
#170000000
1#
b01001 $
1'
b01001 (
#180000000
0#
0'
#190000000
1#
b01010 $
1'
b01010 (
#200000000
0#
0'
#210000000
1#
b01011 $
1'
b01011 (
#220000000
0#
0'
#230000000
1#
b01100 $
1'
b01100 (
#240000000
0#
0'
#250000000
1#
b01101 $
1'
b01101 (
#260000000
0#
0'
#270000000
1#
b01110 $
1'
b01110 (
#280000000
0#
0'
#290000000
1#
b01111 $
1'
b01111 (
#300000000
0#
0'
#310000000
1#
b10000 $
1'
b10000 (
#320000000
0#
0'
#330000000
1#
b10001 $
1'
b10001 (
#340000000
0#
0'
#350000000
1#
b10010 $
1'
b10010 (
#360000000
0#
0'
#370000000
1#
b10011 $
1'
b10011 (
#380000000
0#
0'
#390000000
1#
b10100 $
1'
b10100 (
#400000000
0#
0'
#410000000
1#
b10101 $
1'
b10101 (
#420000000
0#
0'
#430000000
1#
b10110 $
1'
b10110 (
#440000000
0#
0'
#450000000
1#
b10111 $
1'
b10111 (
#460000000
0#
0'
#470000000
1#
b11000 $
1'
b11000 (
#480000000
0#
0'
#490000000
1#
b11001 $
1'
b11001 (
#500000000
0#
0'
#510000000
1#
b11010 $
1'
b11010 (
#520000000
0#
0'
#530000000
1#
b11011 $
1'
b11011 (
#540000000
0#
0'
#550000000
1#
b11100 $
1'
b11100 (
#560000000
0#
0'
#570000000
1#
b11101 $
1'
b11101 (
#580000000
0#
0'
#590000000
1#
b11110 $
1'
b11110 (
#600000000
0#
0'
#610000000
1#
b11111 $
1'
b11111 (
#620000000
0#
0'
#630000000
1#
b00000 $
1'
b00000 (
#640000000
0#
0'
#650000000
1#
b00001 $
1'
b00001 (
#660000000
0#
0'
#670000000
1#
b00010 $
1'
b00010 (
#680000000
0#
0'
#690000000
1#
b00011 $
1'
b00011 (
#700000000
0#
0'
#710000000
1#
b00100 $
1'
b00100 (
#720000000
0#
0'
#730000000
1#
b00101 $
1'
b00101 (
#740000000
0#
0'
#750000000
1#
b00110 $
1'
b00110 (
#760000000
0#
0'
#770000000
1#
b00111 $
1'
b00111 (
#780000000
0#
0'
#790000000
1#
b01000 $
1'
b01000 (
#800000000
0#
0'
#810000000
1#
b01001 $
1'
b01001 (
#820000000
0#
0'
#830000000
1#
b01010 $
1'
b01010 (
#840000000
0#
0'
#850000000
1#
b01011 $
1'
b01011 (
#860000000
0#
0'
#870000000
1#
b01100 $
1'
b01100 (
#880000000
0#
0'
#890000000
1#
b01101 $
1'
b01101 (
#900000000
0#
0'
#910000000
1#
b01110 $
1'
b01110 (
#920000000
0#
0'
#930000000
1#
b01111 $
1'
b01111 (
#940000000
0#
0'
#950000000
1#
b10000 $
1'
b10000 (
#960000000
0#
0'
#970000000
1#
b10001 $
1'
b10001 (
#980000000
0#
0'
#990000000
1#
b10010 $
1'
b10010 (
