bcd_counter_behavioral/src/bcd_counter_behavioral.vhd
library IEEE;
use IEEE.std_logic_1164.all;
use ieee.numeric_std.all;

entity bcd_counter_behavioral is
    port(
        en: in std_logic; 
        clk: in std_logic;
        q: out std_logic_vector(3 downto 0) := (others => '0');
        c_o: out std_logic := '0'
    );
end;

architecture bcd_counter_behavioral_arch of bcd_counter_behavioral is
    begin 
    process(clk)
        variable cnt: unsigned(3 downto 0) := (others => '0');
        begin
            if(clk = '1') then
                c_o <= '0';
                if (en = '1') then
                    cnt := cnt + 1;
                    if cnt = 10 then
                        cnt := (others => '0');
                        c_o <= '1';
                    end if;
                    q <= std_logic_vector(cnt);
                end if;
            end if;
    end process; 
  end;

bcd_counter_behavioral/src/bcd_counter_behavioral_tb.vhd
library IEEE;
use IEEE.std_logic_1164.all;

entity bcd_counter_behavioral_tb is
end;

architecture bcd_counter_behavioral_tb_arch of bcd_counter_behavioral_tb is
    -- Component Declaration --
    component bcd_counter_behavioral is
        port(
            en: in std_logic; 
            clk: in std_logic;
            q: out std_logic_vector(3 downto 0) := (others => '0');
            c_o: out std_logic := '0'
        );
    end component;

    -- Signals Definition --
    signal en_tb: std_logic := '1'; 
    signal clk_tb: std_logic := '0';
    signal q_tb: std_logic_vector(3 downto 0);
    signal c_o_tb: std_logic;

begin

    clk_tb <= not clk_tb after 10 ns;

    -- Sequence Goes Here --
    DUT: bcd_counter_behavioral
        port map(
            en => en_tb,
            clk => clk_tb,
            q => q_tb,
            c_o => c_o_tb
        );
    
    TEST: process
    begin
        wait for 20*9 ns;
        assert q_tb = "1001" report "bcd_counter_behavioral failed" severity failure;
        assert c_o_tb = '0'report "bcd_counter_behavioral failed" severity failure;
        wait for 20 ns;
        assert q_tb = "0000" report "bcd_counter_behavioral failed" severity failure;
        assert c_o_tb = '1'report "bcd_counter_behavioral failed" severity failure;
        wait;
    end process;
end;

bcd_counter_behavioral/sim/bcd_counter_behavioral_tb.vcd
$date
  Sun Sep 12 12:17:04 2021
$end
$version
  GHDL v0
$end
$timescale
  1 fs
$end
$scope module standard $end
$upscope $end
$scope module std_logic_1164 $end
$upscope $end
$scope module numeric_std $end
$upscope $end
$scope module bcd_counter_behavioral_tb $end
$var reg 1 ! en_tb $end
$var reg 1 " clk_tb $end
$var reg 4 # q_tb[3:0] $end
$var reg 1 $ c_o_tb $end
$scope module dut $end
$var reg 1 % en $end
$var reg 1 & clk $end
$var reg 4 ' q[3:0] $end
$var reg 1 ( c_o $end
$upscope $end
$upscope $end
$enddefinitions $end
#0
1!
0"
b0000 #
0$
1%
0&
b0000 '
0(
#10000000
1"
b0001 #
1&
b0001 '
#20000000
0"
0&
#30000000
1"
b0010 #
1&
b0010 '
#40000000
0"
0&
#50000000
1"
b0011 #
1&
b0011 '
#60000000
0"
0&
#70000000
1"
b0100 #
1&
b0100 '
#80000000
0"
0&
#90000000
1"
b0101 #
1&
b0101 '
#100000000
0"
0&
#110000000
1"
b0110 #
1&
b0110 '
#120000000
0"
0&
#130000000
1"
b0111 #
1&
b0111 '
#140000000
0"
0&
#150000000
1"
b1000 #
1&
b1000 '
#160000000
0"
0&
#170000000
1"
b1001 #
1&
b1001 '
#180000000
0"
0&
#190000000
1"
b0000 #
1$
1&
b0000 '
1(
#200000000
0"
0&
#210000000
1"
b0001 #
0$
1&
b0001 '
0(
#220000000
0"
0&
#230000000
1"
b0010 #
1&
b0010 '
#240000000
0"
0&
#250000000
1"
b0011 #
1&
b0011 '
#260000000
0"
0&
#270000000
1"
b0100 #
1&
b0100 '
#280000000
0"
0&
#290000000
1"
b0101 #
1&
b0101 '
#300000000
0"
0&
#310000000
1"
b0110 #
1&
b0110 '
#320000000
0"
0&
#330000000
1"
b0111 #
1&
b0111 '
#340000000
0"
0&
#350000000
1"
b1000 #
1&
b1000 '
#360000000
0"
0&
#370000000
1"
b1001 #
1&
b1001 '
#380000000
0"
0&
#390000000
1"
b0000 #
1$
1&
b0000 '
1(
#400000000
0"
0&
#410000000
1"
b0001 #
0$
1&
b0001 '
0(
#420000000
0"
0&
#430000000
1"
b0010 #
1&
b0010 '
#440000000
0"
0&
#450000000
1"
b0011 #
1&
b0011 '
#460000000
0"
0&
#470000000
1"
b0100 #
1&
b0100 '
#480000000
0"
0&
#490000000
1"
b0101 #
1&
b0101 '
#500000000
0"
0&
#510000000
1"
b0110 #
1&
b0110 '
#520000000
0"
0&
#530000000
1"
b0111 #
1&
b0111 '
#540000000
0"
0&
#550000000
1"
b1000 #
1&
b1000 '
#560000000
0"
0&
#570000000
1"
b1001 #
1&
b1001 '
#580000000
0"
0&
#590000000
1"
b0000 #
1$
1&
b0000 '
1(
#600000000
0"
0&
#610000000
1"
b0001 #
0$
1&
b0001 '
0(
#620000000
0"
0&
#630000000
1"
b0010 #
1&
b0010 '
#640000000
0"
0&
#650000000
1"
b0011 #
1&
b0011 '
#660000000
0"
0&
#670000000
1"
b0100 #
1&
b0100 '
#680000000
0"
0&
#690000000
1"
b0101 #
1&
b0101 '
#700000000
0"
0&
#710000000
1"
b0110 #
1&
b0110 '
#720000000
0"
0&
#730000000
1"
b0111 #
1&
b0111 '
#740000000
0"
0&
#750000000
1"
b1000 #
1&
b1000 '
#760000000
0"
0&
#770000000
1"
b1001 #
1&
b1001 '
#780000000
0"
0&
#790000000
1"
b0000 #
1$
1&
b0000 '
1(
#800000000
0"
0&
#810000000
1"
b0001 #
0$
1&
b0001 '
0(
#820000000
0"
0&
#830000000
1"
b0010 #
1&
b0010 '
#840000000
0"
0&
#850000000
1"
b0011 #
1&
b0011 '
#860000000
0"
0&
#870000000
1"
b0100 #
1&
b0100 '
#880000000
0"
0&
#890000000
1"
b0101 #
1&
b0101 '
#900000000
0"
0&
#910000000
1"
b0110 #
1&
b0110 '
#920000000
0"
0&
#930000000
1"
b0111 #
1&
b0111 '
#940000000
0"
0&
#950000000
1"
b1000 #
1&
b1000 '
#960000000
0"
0&
#970000000
1"
b1001 #
1&
b1001 '
#980000000
0"
0&
#990000000
1"
b0000 #
1$
1&
b0000 '
1(
